pcap2map/IP2Location.py
pcap2map/__init__.py
pcap2map/__main__.py
pcap2map/conftest.py
pcap2map/ip2map.py
pcap2map/pcap2ip.py
pcap2map/pcap2map.py
pcap2map/data/ip.BIN
pcap2map-0.0.1.dist-info/METADATA
pcap2map-0.0.1.dist-info/WHEEL
pcap2map-0.0.1.dist-info/top_level.txt
pcap2map-0.0.1.dist-info/RECORD
