Metadata-Version: 2.1
Name: pcap2map
Version: 0.0.1
Summary: Put IP addresses from PCAP on map
Home-page: https://github.com/jspeed-meyers/pcap2map
Author: John Speed Meyers
Author-email: anon@gmail.com
License: UNKNOWN
Keywords: pcap networking IP geolocation
Platform: UNKNOWN
Classifier: Programming Language :: Python :: 3
Classifier: License :: OSI Approved :: MIT License
Classifier: Operating System :: OS Independent
Classifier: Topic :: System :: Networking
Classifier: Intended Audience :: System Administrators
Requires-Python: >=3.7.6
Requires-Dist: pandas
Requires-Dist: plotly
Requires-Dist: pyshark
